[
  {
    "Id": 0,
    "Title": "RoleInfluence_0_Title",
    "BackGround": "",
    "InfluenceId": 0,
    "CountryId": 0,
    "FilterIcon": "/Game/Aki/UI/UIResources/UiRole/Atlas/SP_RoleTabQuanBu.SP_RoleTabQuanBu",
    "Role": {
      "J7": {
        "bytes_": [
          24,
          0,
          0,
          0,
          0,
          0,
          18,
          0,
          22,
          0,
          0,
          0,
          16,
          0,
          12,
          0,
          0,
          0,
          0,
          0,
          8,
          0,
          4,
          0,
          18,
          0,
          0,
          0,
          24,
          0,
          0,
          0,
          60,
          0,
          0,
          0,
          132,
          0,
          0,
          0,
          136,
          0,
          0,
          0,
          0,
          0,
          6,
          0,
          8,
          0,
          4,
          0,
          6,
          0,
          0,
          0,
          4,
          0,
          0,
          0,
          7,
          0,
          0,
          0,
          79,
          4,
          0,
          0,
          122,
          5,
          0,
          0,
          178,
          4,
          0,
          0,
          179,
          4,
          0,
          0,
          124,
          5,
          0,
          0,
          22,
          5,
          0,
          0,
          80,
          4,
          0,
          0,
          71,
          0,
          0,
          0,
          47,
          71,
          97,
          109,
          101,
          47,
          65,
          107,
          105,
          47,
          85,
          73,
          47,
          85,
          73,
          82,
          101,
          115,
          111,
          117,
          114,
          99,
          101,
          115,
          47,
          85,
          105,
          82,
          111,
          108,
          101,
          47,
          65,
          116,
          108,
          97,
          115,
          47,
          83,
          80,
          95,
          82,
          111,
          108,
          101,
          84,
          97,
          98,
          81,
          117,
          97,
          110,
          66,
          117,
          46,
          83,
          80,
          95,
          82,
          111,
          108,
          101,
          84,
          97,
          98,
          81,
          117,
          97,
          110,
          66,
          117,
          0,
          0,
          0,
          0,
          0,
          0,
          0,
          0,
          0,
          21,
          0,
          0,
          0,
          82,
          111,
          108,
          101,
          73,
          110,
          102,
          108,
          117,
          101,
          110,
          99,
          101,
          95,
          48,
          95,
          84,
          105,
          116,
          108,
          101,
          0,
          0,
          0
        ],
        "position_": 0,
        "text_decoder_": {}
      },
      "z7": 52
    }
  },
  {
    "Id": 2,
    "Title": "RoleInfluence_2_Title",
    "BackGround": "/Game/Aki/UI/UIResources/UiQuest/Image/BG/T_IconChuanShubg_UI.T_IconChuanShubg_UI",
    "InfluenceId": 0,
    "CountryId": 0,
    "FilterIcon": "/Game/Aki/UI/UIResources/UiRole/Atlas/SP_RoleTabHeiHaiAn.SP_RoleTabHeiHaiAn",
    "Role": {
      "J7": {
        "bytes_": [
          24,
          0,
          0,
          0,
          0,
          0,
          18,
          0,
          26,
          0,
          20,
          0,
          16,
          0,
          12,
          0,
          0,
          0,
          0,
          0,
          8,
          0,
          4,
          0,
          18,
          0,
          0,
          0,
          28,
          0,
          0,
          0,
          40,
          0,
          0,
          0,
          116,
          0,
          0,
          0,
          200,
          0,
          0,
          0,
          2,
          0,
          0,
          0,
          0,
          0,
          6,
          0,
          8,
          0,
          4,
          0,
          6,
          0,
          0,
          0,
          4,
          0,
          0,
          0,
          1,
          0,
          0,
          0,
          179,
          4,
          0,
          0,
          75,
          0,
          0,
          0,
          47,
          71,
          97,
          109,
          101,
          47,
          65,
          107,
          105,
          47,
          85,
          73,
          47,
          85,
          73,
          82,
          101,
          115,
          111,
          117,
          114,
          99,
          101,
          115,
          47,
          85,
          105,
          82,
          111,
          108,
          101,
          47,
          65,
          116,
          108,
          97,
          115,
          47,
          83,
          80,
          95,
          82,
          111,
          108,
          101,
          84,
          97,
          98,
          72,
          101,
          105,
          72,
          97,
          105,
          65,
          110,
          46,
          83,
          80,
          95,
          82,
          111,
          108,
          101,
          84,
          97,
          98,
          72,
          101,
          105,
          72,
          97,
          105,
          65,
          110,
          0,
          81,
          0,
          0,
          0,
          47,
          71,
          97,
          109,
          101,
          47,
          65,
          107,
          105,
          47,
          85,
          73,
          47,
          85,
          73,
          82,
          101,
          115,
          111,
          117,
          114,
          99,
          101,
          115,
          47,
          85,
          105,
          81,
          117,
          101,
          115,
          116,
          47,
          73,
          109,
          97,
          103,
          101,
          47,
          66,
          71,
          47,
          84,
          95,
          73,
          99,
          111,
          110,
          67,
          104,
          117,
          97,
          110,
          83,
          104,
          117,
          98,
          103,
          95,
          85,
          73,
          46,
          84,
          95,
          73,
          99,
          111,
          110,
          67,
          104,
          117,
          97,
          110,
          83,
          104,
          117,
          98,
          103,
          95,
          85,
          73,
          0,
          0,
          0,
          21,
          0,
          0,
          0,
          82,
          111,
          108,
          101,
          73,
          110,
          102,
          108,
          117,
          101,
          110,
          99,
          101,
          95,
          50,
          95,
          84,
          105,
          116,
          108,
          101,
          0,
          0,
          0
        ],
        "position_": 0,
        "text_decoder_": {}
      },
      "z7": 56
    }
  },
  {
    "Id": 1,
    "Title": "RoleInfluence_1_Title",
    "BackGround": "/Game/Aki/UI/UIResources/UiQuest/Image/BG/T_IconChuanShubg_UI.T_IconChuanShubg_UI",
    "InfluenceId": 0,
    "CountryId": 1,
    "FilterIcon": "/Game/Aki/UI/UIResources/UiRole/Atlas/SP_RoleTabHuangLong.SP_RoleTabHuangLong",
    "Role": {
      "J7": {
        "bytes_": [
          24,
          0,
          0,
          0,
          0,
          0,
          18,
          0,
          30,
          0,
          24,
          0,
          20,
          0,
          16,
          0,
          0,
          0,
          12,
          0,
          8,
          0,
          4,
          0,
          18,
          0,
          0,
          0,
          32,
          0,
          0,
          0,
          64,
          0,
          0,
          0,
          1,
          0,
          0,
          0,
          140,
          0,
          0,
          0,
          224,
          0,
          0,
          0,
          1,
          0,
          0,
          0,
          0,
          0,
          6,
          0,
          8,
          0,
          4,
          0,
          6,
          0,
          0,
          0,
          4,
          0,
          0,
          0,
          6,
          0,
          0,
          0,
          79,
          4,
          0,
          0,
          122,
          5,
          0,
          0,
          178,
          4,
          0,
          0,
          124,
          5,
          0,
          0,
          22,
          5,
          0,
          0,
          80,
          4,
          0,
          0,
          77,
          0,
          0,
          0,
          47,
          71,
          97,
          109,
          101,
          47,
          65,
          107,
          105,
          47,
          85,
          73,
          47,
          85,
          73,
          82,
          101,
          115,
          111,
          117,
          114,
          99,
          101,
          115,
          47,
          85,
          105,
          82,
          111,
          108,
          101,
          47,
          65,
          116,
          108,
          97,
          115,
          47,
          83,
          80,
          95,
          82,
          111,
          108,
          101,
          84,
          97,
          98,
          72,
          117,
          97,
          110,
          103,
          76,
          111,
          110,
          103,
          46,
          83,
          80,
          95,
          82,
          111,
          108,
          101,
          84,
          97,
          98,
          72,
          117,
          97,
          110,
          103,
          76,
          111,
          110,
          103,
          0,
          0,
          0,
          81,
          0,
          0,
          0,
          47,
          71,
          97,
          109,
          101,
          47,
          65,
          107,
          105,
          47,
          85,
          73,
          47,
          85,
          73,
          82,
          101,
          115,
          111,
          117,
          114,
          99,
          101,
          115,
          47,
          85,
          105,
          81,
          117,
          101,
          115,
          116,
          47,
          73,
          109,
          97,
          103,
          101,
          47,
          66,
          71,
          47,
          84,
          95,
          73,
          99,
          111,
          110,
          67,
          104,
          117,
          97,
          110,
          83,
          104,
          117,
          98,
          103,
          95,
          85,
          73,
          46,
          84,
          95,
          73,
          99,
          111,
          110,
          67,
          104,
          117,
          97,
          110,
          83,
          104,
          117,
          98,
          103,
          95,
          85,
          73,
          0,
          0,
          0,
          21,
          0,
          0,
          0,
          82,
          111,
          108,
          101,
          73,
          110,
          102,
          108,
          117,
          101,
          110,
          99,
          101,
          95,
          49,
          95,
          84,
          105,
          116,
          108,
          101,
          0,
          0,
          0
        ],
        "position_": 0,
        "text_decoder_": {}
      },
      "z7": 60
    }
  }
]